pyborsh/__init__.py
pyborsh/enum.py
pyborsh/errors.py
pyborsh/mixin.py
pyborsh/py.typed
pyborsh/reader.py
pyborsh/schema.py
pyborsh/types.py
pyborsh/writer.py
pyborsh-1.0.1.dist-info/METADATA
pyborsh-1.0.1.dist-info/WHEEL
pyborsh-1.0.1.dist-info/RECORD
