Metadata-Version: 2.4
Name: pyborsh
Version: 1.0.1
Summary: Pydantic-native Borsh serialization for Python
Project-URL: Homepage, https://github.com/r-near/pyborsh
Project-URL: Repository, https://github.com/r-near/pyborsh
Author: Ricky
License-Expression: MIT
Keywords: blockchain,borsh,near,pydantic,serialization,solana
Classifier: Development Status :: 3 - Alpha
Classifier: Intended Audience :: Developers
Classifier: License :: OSI Approved :: MIT License
Classifier: Programming Language :: Python :: 3
Classifier: Programming Language :: Python :: 3.11
Classifier: Programming Language :: Python :: 3.12
Classifier: Programming Language :: Python :: 3.13
Classifier: Topic :: Software Development :: Libraries :: Python Modules
Classifier: Typing :: Typed
Requires-Python: >=3.11
Requires-Dist: pydantic>=2.0
Provides-Extra: dev
Requires-Dist: mypy>=1.18; extra == 'dev'
Requires-Dist: pre-commit>=4.0; extra == 'dev'
Requires-Dist: pytest-cov>=6.0; extra == 'dev'
Requires-Dist: pytest>=8.0; extra == 'dev'
Requires-Dist: ruff>=0.14; extra == 'dev'
